winnplib/__init__.py
winnplib-0.1.4.dist-info/METADATA
winnplib-0.1.4.dist-info/WHEEL
winnplib-0.1.4.dist-info/licenses/LICENSE
winnplib-0.1.4.dist-info/RECORD
