Metadata-Version: 2.3
Name: winnplib
Version: 0.1.4
Summary: A simple API to get Windows Media information, including cover art.
Author: Maxplayz7566
License-File: LICENSE
Classifier: License :: OSI Approved :: MIT License
Classifier: Operating System :: OS Independent
Classifier: Programming Language :: Python :: 3 :: Only
Requires-Python: <3.13,>=3.9
Requires-Dist: pillow
Requires-Dist: winrt-windows-foundation
Requires-Dist: winrt-windows-foundation-collections
Requires-Dist: winrt-windows-media
Requires-Dist: winrt-windows-media-control
Requires-Dist: winrt-windows-storage
Requires-Dist: winrt-windows-storage-streams
